{
  "channel_id": "UCPcG3Rt9oYAuFN_LFS4knSA",
  "retrieved_on": "2021-12-05 03:47:37.250700",
  "channel": {
    "kind": "youtube#channel",
    "etag": "Viq0tGFfI6vKDGeuo73EaDDjNi8",
    "id": "UCPcG3Rt9oYAuFN_LFS4knSA",
    "snippet": {
      "title": "ROARING CLIPS",
      "description": "Welcome to ROARING CLIPS 2. \nThe Best Place to Experience Compilation\n\nbusiness inq: metin.cgln@hotmail.de",
      "publishedAt": "2017-04-15T13:32:05Z",
      "thumbnails": {
        "default": {
          "url": "https://yt3.ggpht.com/ytc/AKedOLQCTH1sZO1GQV9kwuTERvey6NkcjKJFsug_bgnqGA=s88-c-k-c0x00ffffff-no-rj",
          "width": 88,
          "height": 88
        },
        "medium": {
          "url": "https://yt3.ggpht.com/ytc/AKedOLQCTH1sZO1GQV9kwuTERvey6NkcjKJFsug_bgnqGA=s240-c-k-c0x00ffffff-no-rj",
          "width": 240,
          "height": 240
        },
        "high": {
          "url": "https://yt3.ggpht.com/ytc/AKedOLQCTH1sZO1GQV9kwuTERvey6NkcjKJFsug_bgnqGA=s800-c-k-c0x00ffffff-no-rj",
          "width": 800,
          "height": 800
        }
      },
      "localized": {
        "title": "ROARING CLIPS",
        "description": "Welcome to ROARING CLIPS 2. \nThe Best Place to Experience Compilation\n\nbusiness inq: metin.cgln@hotmail.de"
      },
      "country": "US"
    },
    "contentDetails": {
      "relatedPlaylists": {
        "likes": "",
        "uploads": "UUPcG3Rt9oYAuFN_LFS4knSA"
      }
    },
    "statistics": {
      "viewCount": "14869279",
      "hiddenSubscriberCount": true,
      "videoCount": "128"
    },
    "brandingSettings": {
      "channel": {
        "title": "ROARING CLIPS",
        "description": "Welcome to ROARING CLIPS 2. \nThe Best Place to Experience Compilation\n\nbusiness inq: metin.cgln@hotmail.de",
        "keywords": "\"roaring clips\" \"roaring clips 2\" \"instant regret\" \"people dying inside\" compilation \"mr karma\" \"the all rounder\" failgag memes \"daily dose of internet\" \"what could go wrong\" \"instant regret\" \"best compilations\" \"funny compilations\"",
        "country": "US"
      },
      "image": {
        "bannerExternalUrl": "https://yt3.ggpht.com/GAyWncUGKqHAc58fEGoYR0x-x7agEakrSbYozN9MD-ai5hMMJ9XWVAMZ07fBaggadrHMUM0a"
      }
    }
  }
}