{
  "channel_id": "UCTrSsPMmZavLbc3Ex7VhjDg",
  "as_of": "2021-12-05 03:47:36.348980",
  "channel": {
    "kind": "youtube#channel",
    "etag": "MPpzSSqCxVyo3md5aXRyyYWys8Y",
    "id": "UCTrSsPMmZavLbc3Ex7VhjDg",
    "snippet": {
      "title": "Brandon Herrera",
      "description": "My name is Brandon Herrera. \nI'm the founder of The AK Guy Inc, as well as the founder and co-owner of Stark Media Group. I also am the one developing the .50 caliber rifle known as the AK-50. I'm a passionate AK Guy, and hope you enjoy the content I post up here and can gain something from it!",
      "customUrl": "brandonherrera",
      "publishedAt": "2014-09-18T19:25:17Z",
      "thumbnails": {
        "default": {
          "url": "https://yt3.ggpht.com/ytc/AKedOLQH6fhsjkUtB8IBknIpXUiCp96at3CDKzTFzGRydg=s88-c-k-c0x00ffffff-no-rj",
          "width": 88,
          "height": 88
        },
        "medium": {
          "url": "https://yt3.ggpht.com/ytc/AKedOLQH6fhsjkUtB8IBknIpXUiCp96at3CDKzTFzGRydg=s240-c-k-c0x00ffffff-no-rj",
          "width": 240,
          "height": 240
        },
        "high": {
          "url": "https://yt3.ggpht.com/ytc/AKedOLQH6fhsjkUtB8IBknIpXUiCp96at3CDKzTFzGRydg=s800-c-k-c0x00ffffff-no-rj",
          "width": 800,
          "height": 800
        }
      },
      "localized": {
        "title": "Brandon Herrera",
        "description": "My name is Brandon Herrera. \nI'm the founder of The AK Guy Inc, as well as the founder and co-owner of Stark Media Group. I also am the one developing the .50 caliber rifle known as the AK-50. I'm a passionate AK Guy, and hope you enjoy the content I post up here and can gain something from it!"
      },
      "country": "US"
    },
    "contentDetails": {
      "relatedPlaylists": {
        "likes": "",
        "uploads": "UUTrSsPMmZavLbc3Ex7VhjDg"
      }
    },
    "statistics": {
      "viewCount": "231679379",
      "subscriberCount": "1460000",
      "hiddenSubscriberCount": false,
      "videoCount": "342"
    },
    "brandingSettings": {
      "channel": {
        "title": "Brandon Herrera",
        "description": "My name is Brandon Herrera. \nI'm the founder of The AK Guy Inc, as well as the founder and co-owner of Stark Media Group. I also am the one developing the .50 caliber rifle known as the AK-50. I'm a passionate AK Guy, and hope you enjoy the content I post up here and can gain something from it!",
        "keywords": "\"50 cal\" business guns ak ak47 entrepreneur \"brandon herrera\" \"the ak guy\" kalashnikov ak50 vlog vlogger \"social media\" ak-50 protoype \"elon musk\" \"tony stark\" hacksmith",
        "unsubscribedTrailer": "LTVoO22uf-8",
        "country": "US"
      },
      "image": {
        "bannerExternalUrl": "https://lh3.googleusercontent.com/R86M22whGuqjwxcmlGiUhM44oxTYEBoT0JDXqQW3OEZ0mskmtWF9oHobqPC-81PLHbyl8Tgchg"
      }
    }
  }
}
