{
  "channel_id": "UC8XMxyg7vUwvy5hHQJo7STg",
  "as_of": "2021-12-05 03:47:35.288796",
  "channel": {
    "kind": "youtube#channel",
    "etag": "QexomV-aCZ5rMoGG6yl_mkRMINY",
    "id": "UC8XMxyg7vUwvy5hHQJo7STg",
    "snippet": {
      "title": "Kristian Aarum",
      "description": "",
      "customUrl": "kizzam7",
      "publishedAt": "2007-07-04T20:43:59Z",
      "thumbnails": {
        "default": {
          "url": "https://yt3.ggpht.com/ytc/AKedOLQ1QqMKqbsgpkm_ul4ux_ToPOslbM_Gli8owPgktgU=s88-c-k-c0x00ffffff-no-rj",
          "width": 88,
          "height": 88
        },
        "medium": {
          "url": "https://yt3.ggpht.com/ytc/AKedOLQ1QqMKqbsgpkm_ul4ux_ToPOslbM_Gli8owPgktgU=s240-c-k-c0x00ffffff-no-rj",
          "width": 240,
          "height": 240
        },
        "high": {
          "url": "https://yt3.ggpht.com/ytc/AKedOLQ1QqMKqbsgpkm_ul4ux_ToPOslbM_Gli8owPgktgU=s800-c-k-c0x00ffffff-no-rj",
          "width": 800,
          "height": 800
        }
      },
      "localized": {
        "title": "Kristian Aarum",
        "description": ""
      }
    },
    "contentDetails": {
      "relatedPlaylists": {
        "likes": "",
        "uploads": "UU8XMxyg7vUwvy5hHQJo7STg"
      }
    },
    "statistics": {
      "viewCount": "5402392",
      "subscriberCount": "1610",
      "hiddenSubscriberCount": false,
      "videoCount": "9"
    },
    "brandingSettings": {
      "channel": {
        "title": "Kristian Aarum",
        "unsubscribedTrailer": "HyU24rr0doo"
      },
      "image": {
        "bannerExternalUrl": "https://lh3.googleusercontent.com/K7DjTn6uykSeN7KJRkZYFUMD0p2DJtBB54guCYVgNCDT_4UcXrd40mKMXzwz_F55WmqA5P4QPw"
      }
    }
  }
}
