{
  "channel_id": "UC1X2pjdP7-Ou1GtJUztUYkg",
  "as_of": "2021-12-05 03:47:36.348948",
  "channel": {
    "kind": "youtube#channel",
    "etag": "cGWKIaABiU1g2bVqJei__Bblaac",
    "id": "UC1X2pjdP7-Ou1GtJUztUYkg",
    "snippet": {
      "title": "falser",
      "description": "",
      "publishedAt": "2005-08-14T23:17:20Z",
      "thumbnails": {
        "default": {
          "url": "https://yt3.ggpht.com/ytc/AKedOLSG_DOGOqSalTqHTagYtZc7ZGSn8NaVxMMc-Q=s88-c-k-c0x00ffffff-no-rj",
          "width": 88,
          "height": 88
        },
        "medium": {
          "url": "https://yt3.ggpht.com/ytc/AKedOLSG_DOGOqSalTqHTagYtZc7ZGSn8NaVxMMc-Q=s240-c-k-c0x00ffffff-no-rj",
          "width": 240,
          "height": 240
        },
        "high": {
          "url": "https://yt3.ggpht.com/ytc/AKedOLSG_DOGOqSalTqHTagYtZc7ZGSn8NaVxMMc-Q=s800-c-k-c0x00ffffff-no-rj",
          "width": 800,
          "height": 800
        }
      },
      "localized": {
        "title": "falser",
        "description": ""
      }
    },
    "contentDetails": {
      "relatedPlaylists": {
        "likes": "",
        "uploads": "UU1X2pjdP7-Ou1GtJUztUYkg"
      }
    },
    "statistics": {
      "viewCount": "136637",
      "subscriberCount": "116",
      "hiddenSubscriberCount": false,
      "videoCount": "96"
    },
    "brandingSettings": {
      "channel": {
        "title": "falser"
      }
    }
  }
}
