{
  "channel_id": "UCMR5qS7_BlPM2zSb9sh6WmA",
  "retrieved_on": "2021-12-05 03:47:32.898711",
  "channel": {
    "kind": "youtube#channel",
    "etag": "8ZI4RcIea74h16Il4ibyI4dpEC0",
    "id": "UCMR5qS7_BlPM2zSb9sh6WmA",
    "snippet": {
      "title": "whateep",
      "description": "I am an indie game developer for Punk Pebble Studio. I am creating gamedev content such as tutorials and devlogs. I hope you have fun and stick around! ",
      "customUrl": "whateep",
      "publishedAt": "2020-03-19T13:12:42.659649Z",
      "thumbnails": {
        "default": {
          "url": "https://yt3.ggpht.com/ytc/AKedOLQMliCgn9R9XSM5h-DkzlT2KjH2PgOZsiU-GuW4=s88-c-k-c0x00ffffff-no-rj",
          "width": 88,
          "height": 88
        },
        "medium": {
          "url": "https://yt3.ggpht.com/ytc/AKedOLQMliCgn9R9XSM5h-DkzlT2KjH2PgOZsiU-GuW4=s240-c-k-c0x00ffffff-no-rj",
          "width": 240,
          "height": 240
        },
        "high": {
          "url": "https://yt3.ggpht.com/ytc/AKedOLQMliCgn9R9XSM5h-DkzlT2KjH2PgOZsiU-GuW4=s800-c-k-c0x00ffffff-no-rj",
          "width": 800,
          "height": 800
        }
      },
      "localized": {
        "title": "whateep",
        "description": "I am an indie game developer for Punk Pebble Studio. I am creating gamedev content such as tutorials and devlogs. I hope you have fun and stick around! "
      },
      "country": "IT"
    },
    "contentDetails": {
      "relatedPlaylists": {
        "likes": "",
        "uploads": "UUMR5qS7_BlPM2zSb9sh6WmA"
      }
    },
    "statistics": {
      "viewCount": "114248",
      "subscriberCount": "2000",
      "hiddenSubscriberCount": false,
      "videoCount": "47"
    },
    "brandingSettings": {
      "channel": {
        "title": "whateep",
        "description": "I am an indie game developer for Punk Pebble Studio. I am creating gamedev content such as tutorials and devlogs. I hope you have fun and stick around! ",
        "keywords": "gamedev \"game development\" indie \"indie dev\" unity \"indie game\"",
        "unsubscribedTrailer": "coJ3xh0ytos",
        "country": "IT"
      },
      "image": {
        "bannerExternalUrl": "https://yt3.ggpht.com/x4UwxdeabnkBvcJeFKNB3qCxfRoChYx41GlS6-yGk4CCTfNZiEt-EqUQFq3JDgDz4g2_y9Hc4Q"
      }
    }
  }
}