{
  "channel_id": "UCGqQrz8HUV98ii7A_Pz1X_Q",
  "as_of": "2021-12-05 03:47:37.948864",
  "channel": {
    "kind": "youtube#channel",
    "etag": "NexZzhM9eCgGjG0BWnvAzfodkfA",
    "id": "UCGqQrz8HUV98ii7A_Pz1X_Q",
    "snippet": {
      "title": "Biology with Animations",
      "description": "With animations we can easily understand, and we can imagine how the methods are actually carried out. In this way we'll be able to create our own text without resorting to other sources. For making these animations, I use only PowerPoint.",
      "publishedAt": "2018-05-29T18:14:56Z",
      "thumbnails": {
        "default": {
          "url": "https://yt3.ggpht.com/ytc/AKedOLSx3tnovRzj76RS79sCxmmEkO9AlFDshc6n6DFU=s88-c-k-c0x00ffffff-no-rj",
          "width": 88,
          "height": 88
        },
        "medium": {
          "url": "https://yt3.ggpht.com/ytc/AKedOLSx3tnovRzj76RS79sCxmmEkO9AlFDshc6n6DFU=s240-c-k-c0x00ffffff-no-rj",
          "width": 240,
          "height": 240
        },
        "high": {
          "url": "https://yt3.ggpht.com/ytc/AKedOLSx3tnovRzj76RS79sCxmmEkO9AlFDshc6n6DFU=s800-c-k-c0x00ffffff-no-rj",
          "width": 800,
          "height": 800
        }
      },
      "localized": {
        "title": "Biology with Animations",
        "description": "With animations we can easily understand, and we can imagine how the methods are actually carried out. In this way we'll be able to create our own text without resorting to other sources. For making these animations, I use only PowerPoint."
      }
    },
    "contentDetails": {
      "relatedPlaylists": {
        "likes": "",
        "uploads": "UUGqQrz8HUV98ii7A_Pz1X_Q"
      }
    },
    "statistics": {
      "viewCount": "6322737",
      "subscriberCount": "85600",
      "hiddenSubscriberCount": false,
      "videoCount": "16"
    },
    "brandingSettings": {
      "channel": {
        "title": "Biology with Animations",
        "description": "With animations we can easily understand, and we can imagine how the methods are actually carried out. In this way we'll be able to create our own text without resorting to other sources. For making these animations, I use only PowerPoint.",
        "unsubscribedTrailer": "ouDY_pxGiIY"
      },
      "image": {
        "bannerExternalUrl": "https://lh3.googleusercontent.com/l77GX0HZGCsE-tRlcqSr1Rw2WAy9edxVGdmek4CUItBw3y83cs-Bjq9keqEG1g7JGWSlPWI-qA"
      }
    }
  }
}
