{
  "channel_id": "UC7qaZ5pg0l0cDKb1y4yhHRQ",
  "retrieved_on": "2021-12-05 03:47:39.693674",
  "channel": {
    "kind": "youtube#channel",
    "etag": "tCRbY4WNrmZ7jR6KsVGtZdd6m6M",
    "id": "UC7qaZ5pg0l0cDKb1y4yhHRQ",
    "snippet": {
      "title": "OxfordQuantumVideo",
      "description": "Recordings of presentations at conferences, seminars, and workshops, affiliated with the Quantum group at the Department of Computer Science of Oxford University",
      "publishedAt": "2012-03-29T16:15:23Z",
      "thumbnails": {
        "default": {
          "url": "https://yt3.ggpht.com/ytc/AKedOLTXOzQ60NHNqTKIAy-SRVlcgMmrzFo883EZg4pl=s88-c-k-c0x00ffffff-no-rj",
          "width": 88,
          "height": 88
        },
        "medium": {
          "url": "https://yt3.ggpht.com/ytc/AKedOLTXOzQ60NHNqTKIAy-SRVlcgMmrzFo883EZg4pl=s240-c-k-c0x00ffffff-no-rj",
          "width": 240,
          "height": 240
        },
        "high": {
          "url": "https://yt3.ggpht.com/ytc/AKedOLTXOzQ60NHNqTKIAy-SRVlcgMmrzFo883EZg4pl=s800-c-k-c0x00ffffff-no-rj",
          "width": 800,
          "height": 800
        }
      },
      "localized": {
        "title": "OxfordQuantumVideo",
        "description": "Recordings of presentations at conferences, seminars, and workshops, affiliated with the Quantum group at the Department of Computer Science of Oxford University"
      }
    },
    "contentDetails": {
      "relatedPlaylists": {
        "likes": "",
        "uploads": "UU7qaZ5pg0l0cDKb1y4yhHRQ"
      }
    },
    "statistics": {
      "viewCount": "277751",
      "subscriberCount": "2310",
      "hiddenSubscriberCount": false,
      "videoCount": "555"
    },
    "brandingSettings": {
      "channel": {
        "title": "OxfordQuantumVideo",
        "description": "Recordings of presentations at conferences, seminars, and workshops, affiliated with the Quantum group at the Department of Computer Science of Oxford University",
        "keywords": "oxford quantum talks archive video"
      }
    }
  }
}