{
  "channel_id": "UCVBNO-wvP0BHCaXcs3ee-Ng",
  "retrieved_on": "2021-12-05 03:47:30.436640",
  "channel": {
    "kind": "youtube#channel",
    "etag": "ek_gfWEvUHcJaa-5pWbrPAb7TwY",
    "id": "UCVBNO-wvP0BHCaXcs3ee-Ng",
    "snippet": {
      "title": "R N Sangshetti",
      "description": "Educational videos",
      "publishedAt": "2017-01-08T07:33:01Z",
      "thumbnails": {
        "default": {
          "url": "https://yt3.ggpht.com/ytc/AKedOLS_CsC85Z3flGQkSCY1O_H3rzveMwuIvSnlsmDfeg=s88-c-k-c0x00ffffff-no-rj",
          "width": 88,
          "height": 88
        },
        "medium": {
          "url": "https://yt3.ggpht.com/ytc/AKedOLS_CsC85Z3flGQkSCY1O_H3rzveMwuIvSnlsmDfeg=s240-c-k-c0x00ffffff-no-rj",
          "width": 240,
          "height": 240
        },
        "high": {
          "url": "https://yt3.ggpht.com/ytc/AKedOLS_CsC85Z3flGQkSCY1O_H3rzveMwuIvSnlsmDfeg=s800-c-k-c0x00ffffff-no-rj",
          "width": 800,
          "height": 800
        }
      },
      "localized": {
        "title": "R N Sangshetti",
        "description": "Educational videos"
      }
    },
    "contentDetails": {
      "relatedPlaylists": {
        "likes": "",
        "uploads": "UUVBNO-wvP0BHCaXcs3ee-Ng"
      }
    },
    "statistics": {
      "viewCount": "60177",
      "subscriberCount": "672",
      "hiddenSubscriberCount": false,
      "videoCount": "101"
    },
    "brandingSettings": {
      "channel": {
        "title": "R N Sangshetti",
        "description": "Educational videos",
        "keywords": "Rajshri Sangshetti"
      },
      "image": {
        "bannerExternalUrl": "https://lh3.googleusercontent.com/Q-DIvWeUGYoyleE9QU-ovMaiOPRNfdtXDgwty993GMxRUIk2Frx1hpvLOSR74x87l5NLbnXjlQ"
      }
    }
  }
}